<preCompilationAnalysis file="F:/WORKSPACE/XMOS/module_avb_1722/src/avb_1722_common.c">
  <fCall global="true" name="ntoh_16"/>
  <fCall global="true" name="ntoh_16.nstackwords"/>
  <fCall global="true" name="ntoh_16.maxcores"/>
  <fCall global="true" name="ntoh_16.maxtimers"/>
  <fCall global="true" name="ntoh_16.maxchanends"/>
  <fCall global="true" name="ntoh_32"/>
  <fCall global="true" name="ntoh_32.nstackwords"/>
  <fCall global="true" name="ntoh_32.maxcores"/>
  <fCall global="true" name="ntoh_32.maxtimers"/>
  <fCall global="true" name="ntoh_32.maxchanends"/>
  <fCall global="true" name="get_64"/>
  <fCall global="true" name="get_64.nstackwords"/>
  <fCall global="true" name="get_64.maxcores"/>
  <fCall global="true" name="get_64.maxtimers"/>
  <fCall global="true" name="get_64.maxchanends"/>
  <fCall global="true" name="set_64"/>
  <fCall global="true" name="set_64.nstackwords"/>
  <fCall global="true" name="set_64.maxcores"/>
  <fCall global="true" name="set_64.maxtimers"/>
  <fCall global="true" name="set_64.maxchanends"/>
  <fCall global="true" name="hton_16"/>
  <fCall global="true" name="hton_16.nstackwords"/>
  <fCall global="true" name="hton_16.maxcores"/>
  <fCall global="true" name="hton_16.maxtimers"/>
  <fCall global="true" name="hton_16.maxchanends"/>
  <fCall global="true" name="hton_32"/>
  <fCall global="true" name="hton_32.nstackwords"/>
  <fCall global="true" name="hton_32.maxcores"/>
  <fCall global="true" name="hton_32.maxtimers"/>
  <fCall global="true" name="hton_32.maxchanends"/>
</preCompilationAnalysis>
